crawlib/__init__.py
crawlib/_version.py
crawlib/cache.py
crawlib/cached_request.py
crawlib/cli.py
crawlib/decode.py
crawlib/decorator.py
crawlib/exc.py
crawlib/status.py
crawlib/time_util.py
crawlib/util.py
crawlib/__pycache__/__init__.cpython-36.pyc
crawlib/__pycache__/_version.cpython-36.pyc
crawlib/__pycache__/cache.cpython-36.pyc
crawlib/__pycache__/cached_request.cpython-36.pyc
crawlib/__pycache__/decode.cpython-36.pyc
crawlib/__pycache__/decorator.cpython-36.pyc
crawlib/__pycache__/exc.cpython-36.pyc
crawlib/__pycache__/status.cpython-36.pyc
crawlib/__pycache__/time_util.cpython-36.pyc
crawlib/__pycache__/util.cpython-36.pyc
crawlib/cf/__init__.py
crawlib/devops/__init__.py
crawlib/devops/config.py
crawlib/docs/__init__.py
crawlib/entity/__init__.py
crawlib/entity/base.py
crawlib/entity/__pycache__/__init__.cpython-36.pyc
crawlib/entity/__pycache__/base.cpython-36.pyc
crawlib/entity/mongodb/__init__.py
crawlib/entity/mongodb/entity.py
crawlib/entity/mongodb/query_builder.py
crawlib/entity/mongodb/__pycache__/__init__.cpython-36.pyc
crawlib/entity/mongodb/__pycache__/entity.cpython-36.pyc
crawlib/entity/mongodb/__pycache__/query_builder.cpython-36.pyc
crawlib/entity/sql/__init__.py
crawlib/entity/sql/entity.py
crawlib/entity/sql/__pycache__/__init__.cpython-36.pyc
crawlib/entity/sql/__pycache__/entity.cpython-36.pyc
crawlib/example/__init__.py
crawlib/example/__pycache__/__init__.cpython-36.pyc
crawlib/example/scrapy_movie/__init__.py
crawlib/example/scrapy_movie/config.py
crawlib/example/scrapy_movie/db.py
crawlib/example/scrapy_movie/items.py
crawlib/example/scrapy_movie/parser.py
crawlib/example/scrapy_movie/pipelines.py
crawlib/example/scrapy_movie/url_builder.py
crawlib/example/scrapy_movie/__pycache__/__init__.cpython-36.pyc
crawlib/example/scrapy_movie/__pycache__/config.cpython-36.pyc
crawlib/example/scrapy_movie/__pycache__/db.cpython-36.pyc
crawlib/example/scrapy_movie/__pycache__/items.cpython-36.pyc
crawlib-0.1.1.dist-info/AUTHORS.rst
crawlib-0.1.1.dist-info/LICENSE.txt
crawlib-0.1.1.dist-info/METADATA
crawlib-0.1.1.dist-info/WHEEL
crawlib-0.1.1.dist-info/entry_points.txt
crawlib-0.1.1.dist-info/top_level.txt
crawlib-0.1.1.dist-info/RECORD
