Metadata-Version: 2.1
Name: crawlib
Version: 0.1.1
Summary: tool set for crawler project.
Home-page: https://github.com/MacHu-GWU/
Author: Sanhe Hu
Author-email: husanhe@gmail.com
Maintainer: Unknown
License: MIT
Download-URL: https://pypi.python.org/pypi/crawlib/0.1.1#downloads
Platform: Windows
Platform: MacOS
Platform: Unix
Classifier: Development Status :: 4 - Beta
Classifier: Intended Audience :: Developers
Classifier: License :: OSI Approved :: MIT License
Classifier: Natural Language :: English
Classifier: Operating System :: Microsoft :: Windows
Classifier: Operating System :: MacOS
Classifier: Operating System :: Unix
Classifier: Programming Language :: Python
Classifier: Programming Language :: Python :: 2.7
Classifier: Programming Language :: Python :: 3.4
Classifier: Programming Language :: Python :: 3.5
Classifier: Programming Language :: Python :: 3.6
Requires-Dist: requests
Requires-Dist: requests-html
Requires-Dist: beautifulsoup4
Requires-Dist: tabulate
Requires-Dist: rolex (==0.0.8)
Requires-Dist: constant2 (==0.0.13)
Requires-Dist: attrs-mate (==0.0.5)
Requires-Dist: diskcache (==4.1.0)
Requires-Dist: atomicwrites (==1.3.0)
Requires-Dist: loggerFactory (==0.0.5)
Provides-Extra: docs
Requires-Dist: sphinx (==1.8.1) ; extra == 'docs'
Requires-Dist: sphinx-rtd-theme ; extra == 'docs'
Requires-Dist: sphinx-jinja ; extra == 'docs'
Requires-Dist: sphinx-copybutton ; extra == 'docs'
Requires-Dist: docfly (>=0.0.17) ; extra == 'docs'
Requires-Dist: rstobj (>=0.0.5) ; extra == 'docs'
Requires-Dist: pygments ; extra == 'docs'
Provides-Extra: tests
Requires-Dist: pytest (==3.2.3) ; extra == 'tests'
Requires-Dist: pytest-cov (==2.5.1) ; extra == 'tests'
Requires-Dist: pytest-ordering (==0.5) ; extra == 'tests'
Requires-Dist: pathlib-mate ; extra == 'tests'
Requires-Dist: flask ; extra == 'tests'
Requires-Dist: scrapy ; extra == 'tests'
Requires-Dist: configirl (==0.0.7) ; extra == 'tests'
Requires-Dist: mongoengine-mate (==0.0.5) ; extra == 'tests'
Requires-Dist: pymongo-mate (==0.0.4) ; extra == 'tests'
Requires-Dist: sqlalchemy-mate (==0.0.10) ; extra == 'tests'
Requires-Dist: psycopg2-binary (==2.8.4) ; extra == 'tests'
